nest_desktop/__init__.py
nest_desktop/app.py
nest_desktop/app/apple-touch-icon-180x180.png
nest_desktop/app/favicon.ico
nest_desktop/app/index.html
nest_desktop/app/logo.svg
nest_desktop/app/manifest.webmanifest
nest_desktop/app/maskable-icon-512x512.png
nest_desktop/app/pwa-192x192.png
nest_desktop/app/pwa-512x512.png
nest_desktop/app/pwa-64x64.png
nest_desktop/app/registerSW.js
nest_desktop/app/sw.js
nest_desktop/app/workbox-a3cf1d8c.js
nest_desktop/app/assets/config/Activity.json
nest_desktop/app/assets/config/ActivityAxisLabels.json
nest_desktop/app/assets/config/ActivityScatterAnimationGraph.json
nest_desktop/app/assets/config/App.json
nest_desktop/app/assets/config/ColorSchemes.json
nest_desktop/app/assets/config/Connection.json
nest_desktop/app/assets/config/Network.json
nest_desktop/app/assets/config/NetworkGraph.json
nest_desktop/app/assets/config/NetworkGraphWorkspace.json
nest_desktop/app/assets/config/Node.json
nest_desktop/app/assets/config/NodeRecord.json
nest_desktop/app/assets/config/Parameter.json
nest_desktop/app/assets/config/ParameterRandom.json
nest_desktop/app/assets/config/ProjectView.json
nest_desktop/app/assets/config/Simulation.json
nest_desktop/app/assets/css/index-BkK2YzJ3.css
nest_desktop/app/assets/css/vendors/@mdi.css-BJoi0cmu.css
nest_desktop/app/assets/css/vendors/vuetify.css-CEZSyoxr.css
nest_desktop/app/assets/fonts/materialdesignicons-webfont-B7mPwVP_.ttf
nest_desktop/app/assets/fonts/materialdesignicons-webfont-CSr8KVlo.eot
nest_desktop/app/assets/fonts/materialdesignicons-webfont-Dp5v-WZN.woff2
nest_desktop/app/assets/fonts/materialdesignicons-webfont-PXm3-2wK.woff
nest_desktop/app/assets/img/CubehelixDefault-X1N3hVis.png
nest_desktop/app/assets/img/Inferno-BjsXeFlm.png
nest_desktop/app/assets/img/Magma-OFrxUyho.png
nest_desktop/app/assets/img/Plasma-BQxxwvEK.png
nest_desktop/app/assets/img/Rainbow-B7GZxemw.png
nest_desktop/app/assets/img/Viridis-DnJeo9gN.png
nest_desktop/app/assets/img/ebrains-logo-CgeFY5pB.svg
nest_desktop-4.2.0.dist-info/licenses/LICENSE
nest_desktop-4.2.0.dist-info/METADATA
nest_desktop-4.2.0.dist-info/WHEEL
nest_desktop-4.2.0.dist-info/top_level.txt
nest_desktop-4.2.0.dist-info/RECORD
