Metadata-Version: 2.4
Name: nest-desktop
Version: 4.2.0
Summary: A web-based GUI application for spiking neuronal networks
Author-email: Sebastian Spreizer <spreizer@web.de>
Maintainer-email: Sebastian Spreizer <spreizer@web.de>
Project-URL: homepage, https://nest-desktop.github.io
Project-URL: repository, https://github.com/nest-desktop/nest-desktop
Project-URL: documentation, https://nest-desktop.readthedocs.io
Keywords: spiking neuronal networks,simulation,NEST,NESTML,Norse
Classifier: Development Status :: 5 - Production/Stable
Classifier: Intended Audience :: Education
Classifier: Intended Audience :: End Users/Desktop
Classifier: Intended Audience :: Science/Research
Classifier: Topic :: Education
Classifier: Topic :: Scientific/Engineering
Classifier: Topic :: Scientific/Engineering :: Mathematics
Classifier: Topic :: Scientific/Engineering :: Artificial Intelligence
Classifier: Operating System :: OS Independent
Classifier: Programming Language :: Python :: 3.10
Classifier: Programming Language :: Python :: 3.11
Classifier: Programming Language :: Python :: 3.12
Classifier: Programming Language :: Python :: 3.13
Requires-Python: >=3.10
License-File: LICENSE
Dynamic: license-file
